<PAMDataset>
  <PAMRasterBand band="1">
    <Histograms>
      <HistItem>
        <HistMin>-0.0006000000000000001</HistMin>
        <HistMax>32504</HistMax>
        <BucketCount>256</BucketCount>
        <IncludeOutOfRange>1</IncludeOutOfRange>
        <Approximate>0</Approximate>
        <HistCounts>68|1|1|0|3|2|3|3|0|1|2|5|2|1|1|3|0|3|1|1|6|5|2|2|4|3|5|5|1|6|1|5|3|10|7|10|6|8|10|4|5|9|6|6|13|13|16|11|15|7|6|14|18|12|17|19|26|23|28|33|40|38|52|46|37|50|47|34|54|51|55|62|72|59|63|79|78|72|69|81|78|72|70|80|83|116|116|124|136|146|142|154|191|197|231|230|262|311|281|303|351|357|496|572|566|533|650|678|983|1017|1527|3126|2426|5417|2756|4792|3831|4730|16097|63967|89121|21715|47312|31877|117873|52747|177703|333258|540806|235895|234898|195666|169569|136209|117437|101965|106277|73477|61303|53158|46528|37439|33193|27316|22935|19944|16632|13862|11917|10360|8385|7155|6073|4730|4020|3268|2649|2278|1927|1522|1461|1223|1064|903|821|778|724|738|614|585|536|562|485|339|293|287|268|239|239|196|232|64|60|56|51|43|52|44|37|35|45|34|35|42|35|31|34|30|29|29|19|5|5|4|1|4|2|3|2|0|3|2|2|2|6|5|1|3|1|1|1|1|2|2|0|1|0|0|0|0|1|1|0|0|1|1|2|1|0|0|0|1|1|0|1|0|0|0|0|0|0|1|1|0|0|1</HistCounts>
      </HistItem>
    </Histograms>
    <Metadata>
      <MDI key="STATISTICS_COUNT">3313698.000000</MDI>
      <MDI key="STATISTICS_COVARIANCES">840273.7837275449</MDI>
      <MDI key="STATISTICS_EXCLUDEDVALUES"></MDI>
      <MDI key="STATISTICS_MAXIMUM">32504</MDI>
      <MDI key="STATISTICS_MEAN">16684.840360897</MDI>
      <MDI key="STATISTICS_MEDIAN">16443.199704</MDI>
      <MDI key="STATISTICS_MINIMUM">-0.0006</MDI>
      <MDI key="STATISTICS_SKIPFACTORX">1</MDI>
      <MDI key="STATISTICS_SKIPFACTORY">1</MDI>
      <MDI key="STATISTICS_STDDEV">916.66448809122</MDI>
    </Metadata>
  </PAMRasterBand>
</PAMDataset>
